conflux_s3_utils/__init__.py
conflux_s3_utils/py.typed
conflux_s3_utils/s3client.py
conflux_s3_utils/s3uri.py
conflux_s3_utils-0.1.1.dist-info/licenses/LICENSE
conflux_s3_utils-0.1.1.dist-info/METADATA
conflux_s3_utils-0.1.1.dist-info/WHEEL
conflux_s3_utils-0.1.1.dist-info/top_level.txt
conflux_s3_utils-0.1.1.dist-info/RECORD
