Metadata-Version: 2.4
Name: conflux-s3-utils
Version: 0.1.1
Summary: Type-safe interfaces and convenient utilities for interacting with objects in S3.
Author: Conflux
Maintainer: Conflux
License-Expression: Apache-2.0
Project-URL: Repository, https://github.com/conflux-xyz/conflux-s3-utils
Project-URL: Issues, https://github.com/conflux-xyz/conflux-s3-utils/issues
Project-URL: Documentation, https://github.conflux.xyz/conflux-s3-utils
Requires-Python: >=3.12
License-File: LICENSE
Requires-Dist: boto3>=1
Requires-Dist: fsspec>=2024
Dynamic: license-file
